{"course": "BIOL3207", "description": "Animal Behaviour", "year": "2017", "enrolled": 73, "responses": 38, "rate": "52.05%", "semester": 1, "q1": {"description": "Understand Aims & Goals", "strong_agree": {"value": 25, "total": 38, "percent": 65.79}, "agree": {"value": 12, "total": 38, "percent": 31.58}, "neutral": {"value": 0, "total": 38, "percent": 0}, "disagree": {"value": 1, "total": 38, "percent": 2.63}, "strong_disagree": {"value": 0, "total": 38, "percent": 0}}, "q2": {"description": "Intellectually Stimulating", "strong_agree": {"value": 29, "total": 38, "percent": 76.32}, "agree": {"value": 8, "total": 38, "percent": 21.05}, "neutral": {"value": 1, "total": 38, "percent": 2.63}, "disagree": {"value": 0, "total": 38, "percent": 0}, "strong_disagree": {"value": 0, "total": 38, "percent": 0}}, "q3": {"description": "Well Structured", "strong_agree": {"value": 27, "total": 38, "percent": 71.05}, "agree": {"value": 9, "total": 38, "percent": 23.68}, "neutral": {"value": 1, "total": 38, "percent": 2.63}, "disagree": {"value": 1, "total": 38, "percent": 2.63}, "strong_disagree": {"value": 0, "total": 38, "percent": 0}}, "q4": {"description": "Learning Materials Assisted", "strong_agree": {"value": 22, "total": 38, "percent": 57.89}, "agree": {"value": 13, "total": 38, "percent": 34.21}, "neutral": {"value": 3, "total": 38, "percent": 7.89}, "disagree": {"value": 0, "total": 38, "percent": 0}, "strong_disagree": {"value": 0, "total": 38, "percent": 0}}, "q5": {"description": "Assessment Reqs Clear", "strong_agree": {"value": 22, "total": 38, "percent": 57.89}, "agree": {"value": 13, "total": 38, "percent": 34.21}, "neutral": {"value": 1, "total": 38, "percent": 2.63}, "disagree": {"value": 1, "total": 38, "percent": 2.63}, "strong_disagree": {"value": 1, "total": 38, "percent": 2.63}}, "q6": {"description": "Received Helpful Feedback", "strong_agree": {"value": 21, "total": 38, "percent": 55.26}, "agree": {"value": 11, "total": 38, "percent": 28.95}, "neutral": {"value": 4, "total": 38, "percent": 10.53}, "disagree": {"value": 2, "total": 38, "percent": 5.26}, "strong_disagree": {"value": 0, "total": 38, "percent": 0}}, "q7": {"description": "Learned a lot", "strong_agree": {"value": 26, "total": 38, "percent": 68.42}, "agree": {"value": 11, "total": 38, "percent": 28.95}, "neutral": {"value": 1, "total": 38, "percent": 2.63}, "disagree": {"value": 0, "total": 38, "percent": 0}, "strong_disagree": {"value": 0, "total": 38, "percent": 0}}, "q8": {"description": "Overalll Rating", "strong_agree": {"value": 26, "total": 38, "percent": 68.42}, "agree": {"value": 11, "total": 38, "percent": 28.95}, "neutral": {"value": 1, "total": 38, "percent": 2.63}, "disagree": {"value": 0, "total": 38, "percent": 0}, "strong_disagree": {"value": 0, "total": 38, "percent": 0}}}