{"course": "PSYC3102", "description": "Psychopathology", "year": "2014", "enrolled": 457, "responses": 79, "rate": "17.29%", "semester": 1, "q1": {"description": "Understand Aims & Goals", "strong_agree": {"value": 13, "total": 79, "percent": 16.46}, "agree": {"value": 41, "total": 79, "percent": 51.9}, "neutral": {"value": 16, "total": 79, "percent": 20.25}, "disagree": {"value": 8, "total": 79, "percent": 10.13}, "strong_disagree": {"value": 1, "total": 79, "percent": 1.27}}, "q2": {"description": "Intellectually Stimulating", "strong_agree": {"value": 11, "total": 78, "percent": 14.1}, "agree": {"value": 38, "total": 78, "percent": 48.72}, "neutral": {"value": 18, "total": 78, "percent": 23.08}, "disagree": {"value": 8, "total": 78, "percent": 10.26}, "strong_disagree": {"value": 3, "total": 78, "percent": 3.85}}, "q3": {"description": "Well Structured", "strong_agree": {"value": 10, "total": 79, "percent": 12.66}, "agree": {"value": 45, "total": 79, "percent": 56.96}, "neutral": {"value": 18, "total": 79, "percent": 22.78}, "disagree": {"value": 5, "total": 79, "percent": 6.33}, "strong_disagree": {"value": 1, "total": 79, "percent": 1.27}}, "q4": {"description": "Learning Materials Assisted", "strong_agree": {"value": 10, "total": 79, "percent": 12.66}, "agree": {"value": 41, "total": 79, "percent": 51.9}, "neutral": {"value": 19, "total": 79, "percent": 24.05}, "disagree": {"value": 7, "total": 79, "percent": 8.86}, "strong_disagree": {"value": 2, "total": 79, "percent": 2.53}}, "q5": {"description": "Assessment Reqs Clear", "strong_agree": {"value": 15, "total": 78, "percent": 19.23}, "agree": {"value": 36, "total": 78, "percent": 46.15}, "neutral": {"value": 18, "total": 78, "percent": 23.08}, "disagree": {"value": 7, "total": 78, "percent": 8.97}, "strong_disagree": {"value": 2, "total": 78, "percent": 2.56}}, "q6": {"description": "Received Helpful Feedback", "strong_agree": {"value": 3, "total": 77, "percent": 3.9}, "agree": {"value": 14, "total": 77, "percent": 18.18}, "neutral": {"value": 32, "total": 77, "percent": 41.56}, "disagree": {"value": 20, "total": 77, "percent": 25.97}, "strong_disagree": {"value": 8, "total": 77, "percent": 10.39}}, "q7": {"description": "Learned a lot", "strong_agree": {"value": 18, "total": 77, "percent": 23.38}, "agree": {"value": 33, "total": 77, "percent": 42.86}, "neutral": {"value": 19, "total": 77, "percent": 24.68}, "disagree": {"value": 7, "total": 77, "percent": 9.09}, "strong_disagree": {"value": 0, "total": 77, "percent": 0}}, "q8": {"description": "Overalll Rating", "strong_agree": {"value": 9, "total": 79, "percent": 11.39}, "agree": {"value": 38, "total": 79, "percent": 48.1}, "neutral": {"value": 23, "total": 79, "percent": 29.11}, "disagree": {"value": 8, "total": 79, "percent": 10.13}, "strong_disagree": {"value": 1, "total": 79, "percent": 1.27}}}