{"course": "NURS1002", "description": "Adolescents & Young Adults", "year": "2016", "enrolled": 178, "responses": 27, "rate": "15.17%", "semester": 1, "q1": {"description": "Understand Aims & Goals", "strong_agree": {"value": 4, "total": 29, "percent": 13.79}, "agree": {"value": 10, "total": 29, "percent": 34.48}, "neutral": {"value": 8, "total": 29, "percent": 27.59}, "disagree": {"value": 6, "total": 29, "percent": 20.69}, "strong_disagree": {"value": 1, "total": 29, "percent": 3.45}}, "q2": {"description": "Intellectually Stimulating", "strong_agree": {"value": 5, "total": 29, "percent": 17.24}, "agree": {"value": 14, "total": 29, "percent": 48.28}, "neutral": {"value": 6, "total": 29, "percent": 20.69}, "disagree": {"value": 3, "total": 29, "percent": 10.34}, "strong_disagree": {"value": 1, "total": 29, "percent": 3.45}}, "q3": {"description": "Well Structured", "strong_agree": {"value": 5, "total": 29, "percent": 17.24}, "agree": {"value": 6, "total": 29, "percent": 20.69}, "neutral": {"value": 8, "total": 29, "percent": 27.59}, "disagree": {"value": 7, "total": 29, "percent": 24.14}, "strong_disagree": {"value": 3, "total": 29, "percent": 10.34}}, "q4": {"description": "Learning Materials Assisted", "strong_agree": {"value": 3, "total": 29, "percent": 10.34}, "agree": {"value": 11, "total": 29, "percent": 37.93}, "neutral": {"value": 11, "total": 29, "percent": 37.93}, "disagree": {"value": 3, "total": 29, "percent": 10.34}, "strong_disagree": {"value": 1, "total": 29, "percent": 3.45}}, "q5": {"description": "Assessment Reqs Clear", "strong_agree": {"value": 3, "total": 29, "percent": 10.34}, "agree": {"value": 7, "total": 29, "percent": 24.14}, "neutral": {"value": 7, "total": 29, "percent": 24.14}, "disagree": {"value": 9, "total": 29, "percent": 31.03}, "strong_disagree": {"value": 3, "total": 29, "percent": 10.34}}, "q6": {"description": "Received Helpful Feedback", "strong_agree": {"value": 2, "total": 29, "percent": 6.9}, "agree": {"value": 5, "total": 29, "percent": 17.24}, "neutral": {"value": 16, "total": 29, "percent": 55.17}, "disagree": {"value": 3, "total": 29, "percent": 10.34}, "strong_disagree": {"value": 3, "total": 29, "percent": 10.34}}, "q7": {"description": "Learned a lot", "strong_agree": {"value": 6, "total": 27, "percent": 22.22}, "agree": {"value": 9, "total": 27, "percent": 33.33}, "neutral": {"value": 9, "total": 27, "percent": 33.33}, "disagree": {"value": 3, "total": 27, "percent": 11.11}, "strong_disagree": {"value": 0, "total": 27, "percent": 0}}, "q8": {"description": "Overalll Rating", "strong_agree": {"value": 2, "total": 29, "percent": 6.9}, "agree": {"value": 8, "total": 29, "percent": 27.59}, "neutral": {"value": 13, "total": 29, "percent": 44.83}, "disagree": {"value": 5, "total": 29, "percent": 17.24}, "strong_disagree": {"value": 1, "total": 29, "percent": 3.45}}}