{"course": "LAWS3114", "description": "Law of Trusts B", "year": "2015", "enrolled": 299, "responses": 75, "rate": "25.08%", "semester": 2, "q1": {"description": "Understand Aims & Goals", "strong_agree": {"value": 31, "total": 80, "percent": 38.75}, "agree": {"value": 36, "total": 80, "percent": 45}, "neutral": {"value": 9, "total": 80, "percent": 11.25}, "disagree": {"value": 4, "total": 80, "percent": 5}, "strong_disagree": {"value": 0, "total": 80, "percent": 0}}, "q2": {"description": "Intellectually Stimulating", "strong_agree": {"value": 28, "total": 81, "percent": 34.57}, "agree": {"value": 40, "total": 81, "percent": 49.38}, "neutral": {"value": 7, "total": 81, "percent": 8.64}, "disagree": {"value": 4, "total": 81, "percent": 4.94}, "strong_disagree": {"value": 2, "total": 81, "percent": 2.47}}, "q3": {"description": "Well Structured", "strong_agree": {"value": 28, "total": 81, "percent": 34.57}, "agree": {"value": 35, "total": 81, "percent": 43.21}, "neutral": {"value": 12, "total": 81, "percent": 14.81}, "disagree": {"value": 6, "total": 81, "percent": 7.41}, "strong_disagree": {"value": 0, "total": 81, "percent": 0}}, "q4": {"description": "Learning Materials Assisted", "strong_agree": {"value": 28, "total": 80, "percent": 35}, "agree": {"value": 34, "total": 80, "percent": 42.5}, "neutral": {"value": 10, "total": 80, "percent": 12.5}, "disagree": {"value": 5, "total": 80, "percent": 6.25}, "strong_disagree": {"value": 3, "total": 80, "percent": 3.75}}, "q5": {"description": "Assessment Reqs Clear", "strong_agree": {"value": 32, "total": 78, "percent": 41.03}, "agree": {"value": 32, "total": 78, "percent": 41.03}, "neutral": {"value": 10, "total": 78, "percent": 12.82}, "disagree": {"value": 2, "total": 78, "percent": 2.56}, "strong_disagree": {"value": 2, "total": 78, "percent": 2.56}}, "q6": {"description": "Received Helpful Feedback", "strong_agree": {"value": 17, "total": 81, "percent": 20.99}, "agree": {"value": 32, "total": 81, "percent": 39.51}, "neutral": {"value": 15, "total": 81, "percent": 18.52}, "disagree": {"value": 11, "total": 81, "percent": 13.58}, "strong_disagree": {"value": 6, "total": 81, "percent": 7.41}}, "q7": {"description": "Learned a lot", "strong_agree": {"value": 36, "total": 81, "percent": 44.44}, "agree": {"value": 36, "total": 81, "percent": 44.44}, "neutral": {"value": 7, "total": 81, "percent": 8.64}, "disagree": {"value": 1, "total": 81, "percent": 1.23}, "strong_disagree": {"value": 1, "total": 81, "percent": 1.23}}, "q8": {"description": "Overalll Rating", "strong_agree": {"value": 26, "total": 80, "percent": 32.5}, "agree": {"value": 38, "total": 80, "percent": 47.5}, "neutral": {"value": 10, "total": 80, "percent": 12.5}, "disagree": {"value": 5, "total": 80, "percent": 6.25}, "strong_disagree": {"value": 1, "total": 80, "percent": 1.25}}}