{"course": "PUBH7600", "description": "Introduction to Epidemiology", "year": "2017", "enrolled": 185, "responses": 81, "rate": "43.78%", "semester": 1, "q1": {"description": "Understand Aims & Goals", "strong_agree": {"value": 58, "total": 84, "percent": 69.05}, "agree": {"value": 25, "total": 84, "percent": 29.76}, "neutral": {"value": 1, "total": 84, "percent": 1.19}, "disagree": {"value": 0, "total": 84, "percent": 0}, "strong_disagree": {"value": 0, "total": 84, "percent": 0}}, "q2": {"description": "Intellectually Stimulating", "strong_agree": {"value": 54, "total": 84, "percent": 64.29}, "agree": {"value": 26, "total": 84, "percent": 30.95}, "neutral": {"value": 3, "total": 84, "percent": 3.57}, "disagree": {"value": 1, "total": 84, "percent": 1.19}, "strong_disagree": {"value": 0, "total": 84, "percent": 0}}, "q3": {"description": "Well Structured", "strong_agree": {"value": 65, "total": 84, "percent": 77.38}, "agree": {"value": 17, "total": 84, "percent": 20.24}, "neutral": {"value": 1, "total": 84, "percent": 1.19}, "disagree": {"value": 1, "total": 84, "percent": 1.19}, "strong_disagree": {"value": 0, "total": 84, "percent": 0}}, "q4": {"description": "Learning Materials Assisted", "strong_agree": {"value": 56, "total": 84, "percent": 66.67}, "agree": {"value": 26, "total": 84, "percent": 30.95}, "neutral": {"value": 1, "total": 84, "percent": 1.19}, "disagree": {"value": 1, "total": 84, "percent": 1.19}, "strong_disagree": {"value": 0, "total": 84, "percent": 0}}, "q5": {"description": "Assessment Reqs Clear", "strong_agree": {"value": 60, "total": 84, "percent": 71.43}, "agree": {"value": 20, "total": 84, "percent": 23.81}, "neutral": {"value": 3, "total": 84, "percent": 3.57}, "disagree": {"value": 1, "total": 84, "percent": 1.19}, "strong_disagree": {"value": 0, "total": 84, "percent": 0}}, "q6": {"description": "Received Helpful Feedback", "strong_agree": {"value": 45, "total": 83, "percent": 54.22}, "agree": {"value": 27, "total": 83, "percent": 32.53}, "neutral": {"value": 10, "total": 83, "percent": 12.05}, "disagree": {"value": 0, "total": 83, "percent": 0}, "strong_disagree": {"value": 1, "total": 83, "percent": 1.2}}, "q7": {"description": "Learned a lot", "strong_agree": {"value": 53, "total": 83, "percent": 63.86}, "agree": {"value": 27, "total": 83, "percent": 32.53}, "neutral": {"value": 3, "total": 83, "percent": 3.61}, "disagree": {"value": 0, "total": 83, "percent": 0}, "strong_disagree": {"value": 0, "total": 83, "percent": 0}}, "q8": {"description": "Overalll Rating", "strong_agree": {"value": 52, "total": 83, "percent": 62.65}, "agree": {"value": 28, "total": 83, "percent": 33.73}, "neutral": {"value": 3, "total": 83, "percent": 3.61}, "disagree": {"value": 0, "total": 83, "percent": 0}, "strong_disagree": {"value": 0, "total": 83, "percent": 0}}}