{"course": "TOUR2001", "description": "Tourist and Visitor Behaviour", "year": "2015", "enrolled": 231, "responses": 77, "rate": "33.33%", "semester": 2, "q1": {"description": "Understand Aims & Goals", "strong_agree": {"value": 30, "total": 78, "percent": 38.46}, "agree": {"value": 40, "total": 78, "percent": 51.28}, "neutral": {"value": 2, "total": 78, "percent": 2.56}, "disagree": {"value": 4, "total": 78, "percent": 5.13}, "strong_disagree": {"value": 2, "total": 78, "percent": 2.56}}, "q2": {"description": "Intellectually Stimulating", "strong_agree": {"value": 26, "total": 78, "percent": 33.33}, "agree": {"value": 34, "total": 78, "percent": 43.59}, "neutral": {"value": 12, "total": 78, "percent": 15.38}, "disagree": {"value": 4, "total": 78, "percent": 5.13}, "strong_disagree": {"value": 2, "total": 78, "percent": 2.56}}, "q3": {"description": "Well Structured", "strong_agree": {"value": 33, "total": 78, "percent": 42.31}, "agree": {"value": 35, "total": 78, "percent": 44.87}, "neutral": {"value": 5, "total": 78, "percent": 6.41}, "disagree": {"value": 4, "total": 78, "percent": 5.13}, "strong_disagree": {"value": 1, "total": 78, "percent": 1.28}}, "q4": {"description": "Learning Materials Assisted", "strong_agree": {"value": 33, "total": 78, "percent": 42.31}, "agree": {"value": 35, "total": 78, "percent": 44.87}, "neutral": {"value": 5, "total": 78, "percent": 6.41}, "disagree": {"value": 3, "total": 78, "percent": 3.85}, "strong_disagree": {"value": 2, "total": 78, "percent": 2.56}}, "q5": {"description": "Assessment Reqs Clear", "strong_agree": {"value": 34, "total": 78, "percent": 43.59}, "agree": {"value": 34, "total": 78, "percent": 43.59}, "neutral": {"value": 5, "total": 78, "percent": 6.41}, "disagree": {"value": 1, "total": 78, "percent": 1.28}, "strong_disagree": {"value": 4, "total": 78, "percent": 5.13}}, "q6": {"description": "Received Helpful Feedback", "strong_agree": {"value": 32, "total": 78, "percent": 41.03}, "agree": {"value": 27, "total": 78, "percent": 34.62}, "neutral": {"value": 11, "total": 78, "percent": 14.1}, "disagree": {"value": 5, "total": 78, "percent": 6.41}, "strong_disagree": {"value": 3, "total": 78, "percent": 3.85}}, "q7": {"description": "Learned a lot", "strong_agree": {"value": 31, "total": 78, "percent": 39.74}, "agree": {"value": 30, "total": 78, "percent": 38.46}, "neutral": {"value": 14, "total": 78, "percent": 17.95}, "disagree": {"value": 1, "total": 78, "percent": 1.28}, "strong_disagree": {"value": 2, "total": 78, "percent": 2.56}}, "q8": {"description": "Overalll Rating", "strong_agree": {"value": 28, "total": 77, "percent": 36.36}, "agree": {"value": 36, "total": 77, "percent": 46.75}, "neutral": {"value": 10, "total": 77, "percent": 12.99}, "disagree": {"value": 2, "total": 77, "percent": 2.6}, "strong_disagree": {"value": 1, "total": 77, "percent": 1.3}}}