{"course": "JAPN3101", "description": "Continuing Japanese 3", "year": "2015", "enrolled": 66, "responses": 36, "rate": "54.55%", "semester": 1, "q1": {"description": "Understand Aims & Goals", "strong_agree": {"value": 17, "total": 37, "percent": 45.95}, "agree": {"value": 12, "total": 37, "percent": 32.43}, "neutral": {"value": 5, "total": 37, "percent": 13.51}, "disagree": {"value": 2, "total": 37, "percent": 5.41}, "strong_disagree": {"value": 1, "total": 37, "percent": 2.7}}, "q2": {"description": "Intellectually Stimulating", "strong_agree": {"value": 15, "total": 37, "percent": 40.54}, "agree": {"value": 17, "total": 37, "percent": 45.95}, "neutral": {"value": 1, "total": 37, "percent": 2.7}, "disagree": {"value": 4, "total": 37, "percent": 10.81}, "strong_disagree": {"value": 0, "total": 37, "percent": 0}}, "q3": {"description": "Well Structured", "strong_agree": {"value": 16, "total": 37, "percent": 43.24}, "agree": {"value": 15, "total": 37, "percent": 40.54}, "neutral": {"value": 6, "total": 37, "percent": 16.22}, "disagree": {"value": 0, "total": 37, "percent": 0}, "strong_disagree": {"value": 0, "total": 37, "percent": 0}}, "q4": {"description": "Learning Materials Assisted", "strong_agree": {"value": 15, "total": 37, "percent": 40.54}, "agree": {"value": 15, "total": 37, "percent": 40.54}, "neutral": {"value": 3, "total": 37, "percent": 8.11}, "disagree": {"value": 3, "total": 37, "percent": 8.11}, "strong_disagree": {"value": 1, "total": 37, "percent": 2.7}}, "q5": {"description": "Assessment Reqs Clear", "strong_agree": {"value": 19, "total": 37, "percent": 51.35}, "agree": {"value": 12, "total": 37, "percent": 32.43}, "neutral": {"value": 3, "total": 37, "percent": 8.11}, "disagree": {"value": 2, "total": 37, "percent": 5.41}, "strong_disagree": {"value": 1, "total": 37, "percent": 2.7}}, "q6": {"description": "Received Helpful Feedback", "strong_agree": {"value": 14, "total": 36, "percent": 38.89}, "agree": {"value": 15, "total": 36, "percent": 41.67}, "neutral": {"value": 3, "total": 36, "percent": 8.33}, "disagree": {"value": 3, "total": 36, "percent": 8.33}, "strong_disagree": {"value": 1, "total": 36, "percent": 2.78}}, "q7": {"description": "Learned a lot", "strong_agree": {"value": 15, "total": 37, "percent": 40.54}, "agree": {"value": 16, "total": 37, "percent": 43.24}, "neutral": {"value": 2, "total": 37, "percent": 5.41}, "disagree": {"value": 4, "total": 37, "percent": 10.81}, "strong_disagree": {"value": 0, "total": 37, "percent": 0}}, "q8": {"description": "Overalll Rating", "strong_agree": {"value": 15, "total": 37, "percent": 40.54}, "agree": {"value": 14, "total": 37, "percent": 37.84}, "neutral": {"value": 5, "total": 37, "percent": 13.51}, "disagree": {"value": 3, "total": 37, "percent": 8.11}, "strong_disagree": {"value": 0, "total": 37, "percent": 0}}}