{"course": "MATH1050", "description": "Mathematical Foundations", "year": "2017", "enrolled": 373, "responses": 83, "rate": "22.25%", "semester": 1, "q1": {"description": "Understand Aims & Goals", "strong_agree": {"value": 55, "total": 83, "percent": 66.27}, "agree": {"value": 21, "total": 83, "percent": 25.3}, "neutral": {"value": 5, "total": 83, "percent": 6.02}, "disagree": {"value": 2, "total": 83, "percent": 2.41}, "strong_disagree": {"value": 0, "total": 83, "percent": 0}}, "q2": {"description": "Intellectually Stimulating", "strong_agree": {"value": 49, "total": 83, "percent": 59.04}, "agree": {"value": 24, "total": 83, "percent": 28.92}, "neutral": {"value": 7, "total": 83, "percent": 8.43}, "disagree": {"value": 3, "total": 83, "percent": 3.61}, "strong_disagree": {"value": 0, "total": 83, "percent": 0}}, "q3": {"description": "Well Structured", "strong_agree": {"value": 54, "total": 83, "percent": 65.06}, "agree": {"value": 20, "total": 83, "percent": 24.1}, "neutral": {"value": 8, "total": 83, "percent": 9.64}, "disagree": {"value": 1, "total": 83, "percent": 1.2}, "strong_disagree": {"value": 0, "total": 83, "percent": 0}}, "q4": {"description": "Learning Materials Assisted", "strong_agree": {"value": 52, "total": 83, "percent": 62.65}, "agree": {"value": 21, "total": 83, "percent": 25.3}, "neutral": {"value": 8, "total": 83, "percent": 9.64}, "disagree": {"value": 2, "total": 83, "percent": 2.41}, "strong_disagree": {"value": 0, "total": 83, "percent": 0}}, "q5": {"description": "Assessment Reqs Clear", "strong_agree": {"value": 53, "total": 83, "percent": 63.86}, "agree": {"value": 21, "total": 83, "percent": 25.3}, "neutral": {"value": 5, "total": 83, "percent": 6.02}, "disagree": {"value": 4, "total": 83, "percent": 4.82}, "strong_disagree": {"value": 0, "total": 83, "percent": 0}}, "q6": {"description": "Received Helpful Feedback", "strong_agree": {"value": 33, "total": 83, "percent": 39.76}, "agree": {"value": 26, "total": 83, "percent": 31.33}, "neutral": {"value": 18, "total": 83, "percent": 21.69}, "disagree": {"value": 6, "total": 83, "percent": 7.23}, "strong_disagree": {"value": 0, "total": 83, "percent": 0}}, "q7": {"description": "Learned a lot", "strong_agree": {"value": 51, "total": 83, "percent": 61.45}, "agree": {"value": 22, "total": 83, "percent": 26.51}, "neutral": {"value": 7, "total": 83, "percent": 8.43}, "disagree": {"value": 2, "total": 83, "percent": 2.41}, "strong_disagree": {"value": 1, "total": 83, "percent": 1.2}}, "q8": {"description": "Overalll Rating", "strong_agree": {"value": 50, "total": 83, "percent": 60.24}, "agree": {"value": 26, "total": 83, "percent": 31.33}, "neutral": {"value": 5, "total": 83, "percent": 6.02}, "disagree": {"value": 1, "total": 83, "percent": 1.2}, "strong_disagree": {"value": 1, "total": 83, "percent": 1.2}}}