{"course": "ENGG1300", "description": "Intro to Electrical Systems", "year": "2016", "enrolled": 312, "responses": 76, "rate": "24.36%", "semester": 2, "q1": {"description": "Understand Aims & Goals", "strong_agree": {"value": 55, "total": 87, "percent": 63.22}, "agree": {"value": 29, "total": 87, "percent": 33.33}, "neutral": {"value": 3, "total": 87, "percent": 3.45}, "disagree": {"value": 0, "total": 87, "percent": 0}, "strong_disagree": {"value": 0, "total": 87, "percent": 0}}, "q2": {"description": "Intellectually Stimulating", "strong_agree": {"value": 52, "total": 87, "percent": 59.77}, "agree": {"value": 30, "total": 87, "percent": 34.48}, "neutral": {"value": 4, "total": 87, "percent": 4.6}, "disagree": {"value": 1, "total": 87, "percent": 1.15}, "strong_disagree": {"value": 0, "total": 87, "percent": 0}}, "q3": {"description": "Well Structured", "strong_agree": {"value": 52, "total": 87, "percent": 59.77}, "agree": {"value": 30, "total": 87, "percent": 34.48}, "neutral": {"value": 4, "total": 87, "percent": 4.6}, "disagree": {"value": 0, "total": 87, "percent": 0}, "strong_disagree": {"value": 1, "total": 87, "percent": 1.15}}, "q4": {"description": "Learning Materials Assisted", "strong_agree": {"value": 55, "total": 87, "percent": 63.22}, "agree": {"value": 25, "total": 87, "percent": 28.74}, "neutral": {"value": 3, "total": 87, "percent": 3.45}, "disagree": {"value": 3, "total": 87, "percent": 3.45}, "strong_disagree": {"value": 1, "total": 87, "percent": 1.15}}, "q5": {"description": "Assessment Reqs Clear", "strong_agree": {"value": 54, "total": 86, "percent": 62.79}, "agree": {"value": 29, "total": 86, "percent": 33.72}, "neutral": {"value": 3, "total": 86, "percent": 3.49}, "disagree": {"value": 0, "total": 86, "percent": 0}, "strong_disagree": {"value": 0, "total": 86, "percent": 0}}, "q6": {"description": "Received Helpful Feedback", "strong_agree": {"value": 36, "total": 86, "percent": 41.86}, "agree": {"value": 30, "total": 86, "percent": 34.88}, "neutral": {"value": 15, "total": 86, "percent": 17.44}, "disagree": {"value": 3, "total": 86, "percent": 3.49}, "strong_disagree": {"value": 2, "total": 86, "percent": 2.33}}, "q7": {"description": "Learned a lot", "strong_agree": {"value": 53, "total": 87, "percent": 60.92}, "agree": {"value": 27, "total": 87, "percent": 31.03}, "neutral": {"value": 5, "total": 87, "percent": 5.75}, "disagree": {"value": 1, "total": 87, "percent": 1.15}, "strong_disagree": {"value": 1, "total": 87, "percent": 1.15}}, "q8": {"description": "Overalll Rating", "strong_agree": {"value": 53, "total": 85, "percent": 62.35}, "agree": {"value": 26, "total": 85, "percent": 30.59}, "neutral": {"value": 5, "total": 85, "percent": 5.88}, "disagree": {"value": 0, "total": 85, "percent": 0}, "strong_disagree": {"value": 1, "total": 85, "percent": 1.18}}}