{"course": "POLS2603", "description": "World Women", "year": "2014", "enrolled": 67, "responses": 23, "rate": "34.33%", "semester": 1, "q1": {"description": "Understand Aims & Goals", "strong_agree": {"value": 4, "total": 23, "percent": 17.39}, "agree": {"value": 9, "total": 23, "percent": 39.13}, "neutral": {"value": 5, "total": 23, "percent": 21.74}, "disagree": {"value": 5, "total": 23, "percent": 21.74}, "strong_disagree": {"value": 0, "total": 23, "percent": 0}}, "q2": {"description": "Intellectually Stimulating", "strong_agree": {"value": 7, "total": 22, "percent": 31.82}, "agree": {"value": 10, "total": 22, "percent": 45.45}, "neutral": {"value": 5, "total": 22, "percent": 22.73}, "disagree": {"value": 0, "total": 22, "percent": 0}, "strong_disagree": {"value": 0, "total": 22, "percent": 0}}, "q3": {"description": "Well Structured", "strong_agree": {"value": 4, "total": 22, "percent": 18.18}, "agree": {"value": 8, "total": 22, "percent": 36.36}, "neutral": {"value": 5, "total": 22, "percent": 22.73}, "disagree": {"value": 3, "total": 22, "percent": 13.64}, "strong_disagree": {"value": 2, "total": 22, "percent": 9.09}}, "q4": {"description": "Learning Materials Assisted", "strong_agree": {"value": 2, "total": 21, "percent": 9.52}, "agree": {"value": 12, "total": 21, "percent": 57.14}, "neutral": {"value": 5, "total": 21, "percent": 23.81}, "disagree": {"value": 2, "total": 21, "percent": 9.52}, "strong_disagree": {"value": 0, "total": 21, "percent": 0}}, "q5": {"description": "Assessment Reqs Clear", "strong_agree": {"value": 1, "total": 22, "percent": 4.55}, "agree": {"value": 4, "total": 22, "percent": 18.18}, "neutral": {"value": 8, "total": 22, "percent": 36.36}, "disagree": {"value": 5, "total": 22, "percent": 22.73}, "strong_disagree": {"value": 4, "total": 22, "percent": 18.18}}, "q6": {"description": "Received Helpful Feedback", "strong_agree": {"value": 3, "total": 22, "percent": 13.64}, "agree": {"value": 5, "total": 22, "percent": 22.73}, "neutral": {"value": 9, "total": 22, "percent": 40.91}, "disagree": {"value": 4, "total": 22, "percent": 18.18}, "strong_disagree": {"value": 1, "total": 22, "percent": 4.55}}, "q7": {"description": "Learned a lot", "strong_agree": {"value": 4, "total": 21, "percent": 19.05}, "agree": {"value": 5, "total": 21, "percent": 23.81}, "neutral": {"value": 9, "total": 21, "percent": 42.86}, "disagree": {"value": 3, "total": 21, "percent": 14.29}, "strong_disagree": {"value": 0, "total": 21, "percent": 0}}, "q8": {"description": "Overalll Rating", "strong_agree": {"value": 3, "total": 20, "percent": 15}, "agree": {"value": 5, "total": 20, "percent": 25}, "neutral": {"value": 9, "total": 20, "percent": 45}, "disagree": {"value": 3, "total": 20, "percent": 15}, "strong_disagree": {"value": 0, "total": 20, "percent": 0}}}