{"course": "TOUR7031", "description": "Visitor Management", "year": "2014", "enrolled": 174, "responses": 96, "rate": "55.17%", "semester": 1, "q1": {"description": "Understand Aims & Goals", "strong_agree": {"value": 68, "total": 96, "percent": 70.83}, "agree": {"value": 27, "total": 96, "percent": 28.12}, "neutral": {"value": 1, "total": 96, "percent": 1.04}, "disagree": {"value": 0, "total": 96, "percent": 0}, "strong_disagree": {"value": 0, "total": 96, "percent": 0}}, "q2": {"description": "Intellectually Stimulating", "strong_agree": {"value": 54, "total": 96, "percent": 56.25}, "agree": {"value": 40, "total": 96, "percent": 41.67}, "neutral": {"value": 2, "total": 96, "percent": 2.08}, "disagree": {"value": 0, "total": 96, "percent": 0}, "strong_disagree": {"value": 0, "total": 96, "percent": 0}}, "q3": {"description": "Well Structured", "strong_agree": {"value": 66, "total": 96, "percent": 68.75}, "agree": {"value": 29, "total": 96, "percent": 30.21}, "neutral": {"value": 1, "total": 96, "percent": 1.04}, "disagree": {"value": 0, "total": 96, "percent": 0}, "strong_disagree": {"value": 0, "total": 96, "percent": 0}}, "q4": {"description": "Learning Materials Assisted", "strong_agree": {"value": 59, "total": 96, "percent": 61.46}, "agree": {"value": 31, "total": 96, "percent": 32.29}, "neutral": {"value": 3, "total": 96, "percent": 3.12}, "disagree": {"value": 3, "total": 96, "percent": 3.12}, "strong_disagree": {"value": 0, "total": 96, "percent": 0}}, "q5": {"description": "Assessment Reqs Clear", "strong_agree": {"value": 54, "total": 96, "percent": 56.25}, "agree": {"value": 36, "total": 96, "percent": 37.5}, "neutral": {"value": 5, "total": 96, "percent": 5.21}, "disagree": {"value": 1, "total": 96, "percent": 1.04}, "strong_disagree": {"value": 0, "total": 96, "percent": 0}}, "q6": {"description": "Received Helpful Feedback", "strong_agree": {"value": 42, "total": 95, "percent": 44.21}, "agree": {"value": 44, "total": 95, "percent": 46.32}, "neutral": {"value": 7, "total": 95, "percent": 7.37}, "disagree": {"value": 2, "total": 95, "percent": 2.11}, "strong_disagree": {"value": 0, "total": 95, "percent": 0}}, "q7": {"description": "Learned a lot", "strong_agree": {"value": 68, "total": 96, "percent": 70.83}, "agree": {"value": 26, "total": 96, "percent": 27.08}, "neutral": {"value": 2, "total": 96, "percent": 2.08}, "disagree": {"value": 0, "total": 96, "percent": 0}, "strong_disagree": {"value": 0, "total": 96, "percent": 0}}, "q8": {"description": "Overalll Rating", "strong_agree": {"value": 61, "total": 96, "percent": 63.54}, "agree": {"value": 34, "total": 96, "percent": 35.42}, "neutral": {"value": 1, "total": 96, "percent": 1.04}, "disagree": {"value": 0, "total": 96, "percent": 0}, "strong_disagree": {"value": 0, "total": 96, "percent": 0}}}